vpos/__init__.py
vpos/vpos.py
vpos/test/__init__.py
vpos/test/test_vpos.py
vpos-1.0.dist-info/LICENSE
vpos-1.0.dist-info/METADATA
vpos-1.0.dist-info/WHEEL
vpos-1.0.dist-info/top_level.txt
vpos-1.0.dist-info/RECORD
