Metadata-Version: 2.1
Name: vpos
Version: 1.0
Summary: Facilitates the intereaction with Vpos API
Home-page: https://pypi.org/project/vpos/
Author: Ilton Ingui
Author-email: ilton@nextbss.co.ao
License: UNKNOWN
Keywords: nextbss,python,vpos,point of sales,emis
Platform: UNKNOWN
Classifier: Development Status :: 4 - Beta
Classifier: Intended Audience :: Developers
Classifier: License :: OSI Approved :: MIT License
Classifier: Programming Language :: Python :: 3.6
Classifier: Programming Language :: Python :: 3.7
Classifier: Programming Language :: Python :: 3.8
Classifier: Programming Language :: Python :: 3.9
Classifier: Operating System :: MacOS :: MacOS X
Classifier: Operating System :: Microsoft :: Windows
Requires-Dist: pytest
Requires-Dist: requests
